logbull/__init__.py
logbull/py.typed
logbull/core/__init__.py
logbull/core/logger.py
logbull/core/registry.py
logbull/core/sender.py
logbull/core/types.py
logbull/handlers/__init__.py
logbull/handlers/loguru.py
logbull/handlers/standard.py
logbull/handlers/structlog.py
logbull/utils/__init__.py
logbull/utils/formatting.py
logbull/utils/validation.py
logbull-0.8.0.dist-info/METADATA
logbull-0.8.0.dist-info/WHEEL
logbull-0.8.0.dist-info/licenses/LICENSE
logbull-0.8.0.dist-info/RECORD
