Metadata-Version: 2.4
Name: logbull
Version: 0.8.0
Summary: LogBull Python client library for sending logs to LogBull server
Project-URL: Homepage, https://github.com/logbull/logbull
Project-URL: Documentation, https://github.com/logbull/logbull
Project-URL: Repository, https://github.com/logbull/logbull
Project-URL: Issues, https://github.com/logbull/logbull/issues
Author: LogBull Team
License: Apache-2.0
License-File: LICENSE
Keywords: logbull,logging,logs,monitoring
Classifier: Development Status :: 4 - Beta
Classifier: Intended Audience :: Developers
Classifier: License :: OSI Approved :: Apache Software License
Classifier: Programming Language :: Python :: 3
Classifier: Programming Language :: Python :: 3.9
Classifier: Programming Language :: Python :: 3.10
Classifier: Programming Language :: Python :: 3.11
Classifier: Programming Language :: Python :: 3.12
Classifier: Topic :: Software Development :: Libraries :: Python Modules
Classifier: Topic :: System :: Logging
Requires-Python: >=3.9
Provides-Extra: dev
Requires-Dist: loguru>=0.7.0; extra == 'dev'
Requires-Dist: mypy>=1.7.0; extra == 'dev'
Requires-Dist: pre-commit>=3.6.0; extra == 'dev'
Requires-Dist: pytest-cov>=4.1.0; extra == 'dev'
Requires-Dist: pytest>=7.4.3; extra == 'dev'
Requires-Dist: python-semantic-release>=9.0.0; extra == 'dev'
Requires-Dist: ruff>=0.12.4; extra == 'dev'
Requires-Dist: structlog>=23.1.0; extra == 'dev'
